NeuralNetwork.py
QCNN.py
QCNN-1.0.3.dist-info/LICENSE.txt
QCNN-1.0.3.dist-info/METADATA
QCNN-1.0.3.dist-info/WHEEL
QCNN-1.0.3.dist-info/top_level.txt
QCNN-1.0.3.dist-info/RECORD
