Metadata-Version: 2.1
Name: QCNN
Version: 1.0.3
Summary: Deep Neural Network module for classification/regression
Home-page: UNKNOWN
License: UNKNOWN
Platform: UNKNOWN
Classifier: Operating System :: OS Independent
Classifier: Programming Language :: Python
Classifier: License :: OSI Approved :: MIT License
Requires-Dist: matplotlib (>=2.2.2)
Requires-Dist: pandas (>=0.22.0)
Requires-Dist: numpy (>=1.18.2)
